EvoDAG/__init__.py
EvoDAG/bagging_fitness.py
EvoDAG/base.py
EvoDAG/command_line.py
EvoDAG/cython_utils.c
EvoDAG/cython_utils.cp39-win_amd64.pyd
EvoDAG/cython_utils.pyx
EvoDAG/function_selection.c
EvoDAG/function_selection.cp39-win_amd64.pyd
EvoDAG/function_selection.pxd
EvoDAG/function_selection.pyx
EvoDAG/gp.py
EvoDAG/linalg_solve.c
EvoDAG/linalg_solve.cp39-win_amd64.pyd
EvoDAG/linalg_solve.pyx
EvoDAG/model.py
EvoDAG/naive_bayes.py
EvoDAG/node.py
EvoDAG/population.py
EvoDAG/utils.py
EvoDAG/conf/default_parameters.json
EvoDAG/conf/default_parameters_r.json
EvoDAG/conf/parameter_values.json
EvoDAG/tests/test_bagging_fitness.py
EvoDAG/tests/test_command_line.py
EvoDAG/tests/test_function_selection.py
EvoDAG/tests/test_gp.py
EvoDAG/tests/test_model.py
EvoDAG/tests/test_naive_bayes.py
EvoDAG/tests/test_node.py
EvoDAG/tests/test_population.py
EvoDAG/tests/test_root.py
EvoDAG/tests/test_utils.py
EvoDAG-0.17.2.dist-info/LICENSE
EvoDAG-0.17.2.dist-info/METADATA
EvoDAG-0.17.2.dist-info/WHEEL
EvoDAG-0.17.2.dist-info/entry_points.txt
EvoDAG-0.17.2.dist-info/top_level.txt
EvoDAG-0.17.2.dist-info/RECORD
