Metadata-Version: 2.1
Name: EvoDAG
Version: 0.17.2
Summary: Evolving Directed Acyclic Graph
Home-page: https://github.com/mgraffg/EvoDAG
Author: Mario Graff
Author-email: mgraffg@ieee.org
Classifier: Development Status :: 3 - Alpha
Classifier: Environment :: Console
Classifier: Intended Audience :: Science/Research
Classifier: License :: OSI Approved :: Apache Software License
Classifier: Natural Language :: English
Classifier: Operating System :: MacOS :: MacOS X
Classifier: Operating System :: POSIX :: Linux
Classifier: Programming Language :: Python :: 2.7
Classifier: Programming Language :: Python :: 3
Classifier: Topic :: Scientific/Engineering :: Artificial Intelligence
License-File: LICENSE
Requires-Dist: numpy
Requires-Dist: SparseArray
